a_selenium_download_without_asking/LICENSE
a_selenium_download_without_asking/README.MD
a_selenium_download_without_asking/__init__.py
a_selenium_download_without_asking/requirements.txt
a_selenium_download_without_asking/thirdparty.json
a_selenium_download_without_asking-0.10.dist-info/LICENSE.rst
a_selenium_download_without_asking-0.10.dist-info/METADATA
a_selenium_download_without_asking-0.10.dist-info/WHEEL
a_selenium_download_without_asking-0.10.dist-info/top_level.txt
a_selenium_download_without_asking-0.10.dist-info/RECORD
